jupyter_sentry_extension/__init__.py
jupyter_sentry_extension/extension.py
jupyter_sentry_extension-0.0.2.data/data/etc/jupyter/jupyter_server_config.d/jupyter_sentry_extension.json
jupyter_sentry_extension-0.0.2.dist-info/METADATA
jupyter_sentry_extension-0.0.2.dist-info/WHEEL
jupyter_sentry_extension-0.0.2.dist-info/licenses/LICENSE
jupyter_sentry_extension-0.0.2.dist-info/RECORD
