Metadata-Version: 2.1
Name: jupyter_sentry_extension
Version: 0.0.2
Author-email: Pavel Komar <pvkomar@cloud.ru>
License: BSD 3-Clause License
License-File: LICENSE
Keywords: Extension,Jupyter
Classifier: Framework :: Jupyter
Classifier: License :: OSI Approved :: BSD License
Classifier: Programming Language :: Python
Classifier: Programming Language :: Python :: 3
Classifier: Programming Language :: Python :: 3.8
Classifier: Programming Language :: Python :: 3.9
Classifier: Programming Language :: Python :: 3.10
Classifier: Programming Language :: Python :: 3.11
Requires-Python: >=3.8
Requires-Dist: jupyter-server<3,>=1.6
Requires-Dist: sentry-sdk>=1.5.5
Provides-Extra: lint
Requires-Dist: black>=22.6.0; extra == 'lint'
